vershachi/__init__.py
vershachi/federated_unlearning/__init__.py
vershachi/federated_unlearning/data_preprocess.py
vershachi/federated_unlearning/fed_learn_base.py
vershachi/federated_unlearning/fed_unlearn_base.py
vershachi/federated_unlearning/membership_inference.py
vershachi/federated_unlearning/model_initialization.py
vershachi/sisa/__init__.py
vershachi/sisa/aggregation.py
vershachi/sisa/distribution.py
vershachi/sisa/preprocessing.py
vershachi/sisa/sharded.py
vershachi/sisa/sisa.py
vershachi/sisa/time.py
vershachi-0.1.1.dist-info/LICENSE
vershachi-0.1.1.dist-info/METADATA
vershachi-0.1.1.dist-info/WHEEL
vershachi-0.1.1.dist-info/RECORD
